openid_whisperer/__init__.py
openid_whisperer/__main__.py
openid_whisperer/config.py
openid_whisperer/demo_certs/ca_cert.pem
openid_whisperer/demo_certs/cert.pem
openid_whisperer/demo_certs/key.pem
openid_whisperer/main.py
openid_whisperer/openid_blueprint.py
openid_whisperer/openid_interface.py
openid_whisperer/openid_types.py
openid_whisperer/py.typed
openid_whisperer/static/style.css
openid_whisperer/templates/authenticate.html
openid_whisperer/templates/form_post_response.html
openid_whisperer/utils/__init__.py
openid_whisperer/utils/cert_utils.py
openid_whisperer/utils/common.py
openid_whisperer/utils/config_utils.py
openid_whisperer/utils/credential_store.py
openid_whisperer/utils/test_utils.py
openid_whisperer/utils/token_store.py
openid_whisperer/utils/token_utils.py
openid_whisperer/utils/user_info_ext.py
openid_whisperer-0.1.10.dist-info/LICENSE
openid_whisperer-0.1.10.dist-info/METADATA
openid_whisperer-0.1.10.dist-info/WHEEL
openid_whisperer-0.1.10.dist-info/entry_points.txt
openid_whisperer-0.1.10.dist-info/RECORD
