Metadata-Version: 2.1
Name: openid-whisperer
Version: 0.1.10
Summary: OpenID 1.0 Mock Identity Service
Home-page: https://github.com/robertbetts/openid-whisperer
License: MIT
Keywords: python,mock,api,oauth2,openid
Author: Robert Betts
Author-email: betts_robert@yahoo.com
Maintainer: Robert Betts
Maintainer-email: betts_robert@yahoo.com
Requires-Python: >=3.10,<4.0
Classifier: License :: OSI Approved :: MIT License
Classifier: Operating System :: OS Independent
Classifier: Programming Language :: Python :: 3
Classifier: Programming Language :: Python :: 3.10
Classifier: Programming Language :: Python :: 3.11
Requires-Dist: Faker (>=18.13.0,<19.0.0)
Requires-Dist: cryptography (>=41.0.1,<42.0.0)
Requires-Dist: flask-session (>=0.5.0,<0.6.0)
Requires-Dist: flask[async] (>=2.2.3,<3.0.0)
Requires-Dist: pyjwt (>=2.6.0,<3.0.0)
Requires-Dist: python-dotenv (>=1.0.0,<2.0.0)
Requires-Dist: pyyaml (>=6.0,<7.0)
Requires-Dist: requests[security] (>=2.31.0,<3.0.0)
Requires-Dist: types-requests (>=2.31.0.1,<3.0.0.0)
Project-URL: Repository, https://github.com/robertbetts/openid-whisperer
